pypomes_sob/__init__.py
pypomes_sob/sob_config.py
pypomes_sob/sob_pomes.py
pypomes_sob-1.1.1.dist-info/METADATA
pypomes_sob-1.1.1.dist-info/WHEEL
pypomes_sob-1.1.1.dist-info/licenses/LICENSE
pypomes_sob-1.1.1.dist-info/RECORD
