Metadata-Version: 2.4
Name: pypomes_sob
Version: 1.1.1
Summary: A collection of Python pomes, penyeach (simple object module)
Project-URL: Homepage, https://github.com/TheWiseCoder/PyPomes-SOB
Project-URL: Bug Tracker, https://github.com/TheWiseCoder/PyPomes-SOB/issues
Author-email: GT Nunes <wisecoder01@gmail.com>
License-File: LICENSE
Classifier: License :: OSI Approved :: MIT License
Classifier: Operating System :: OS Independent
Classifier: Programming Language :: Python :: 3
Requires-Python: >=3.14
Requires-Dist: pypomes-core>=2.9.6
Requires-Dist: pypomes-db>=2.8.7
